CONTRIBUTING.md
CONTRIBUTORS.md
LICENSE.txt
MANIFEST.in
README.md
setup.cfg
setup.py
tox.ini
version.txt
geckoboard/__about__.py
geckoboard/__init__.py
geckoboard/_version.py
geckoboard/dataset.py
geckoboard/session.py
geckoboard_python.egg-info/PKG-INFO
geckoboard_python.egg-info/SOURCES.txt
geckoboard_python.egg-info/dependency_links.txt
geckoboard_python.egg-info/requires.txt
geckoboard_python.egg-info/top_level.txt