Metadata-Version: 1.0
Name: geckoboard-python
Version: 0.2.0
Summary: Wrapper for the Geckboboard DataSet API
Home-page: https://github.com/helium/geckoboard-python
Author: Helium
Author-email: hello@helium.com
License: BSD
Platform: UNKNOWN
